{"home_team": {"conference": "National", "division": "East", "first_name": "Washington", "last_name": "Nationals", "site_name": "Nationals Park", "city": "Washington", "state": "District of Columbia", "abbreviation": "WAS", "team_id": "washington-nationals", "full_name": "Washington Nationals", "active": true}, "away_team": {"conference": "National", "division": "West", "first_name": "Colorado", "last_name": "Rockies", "site_name": "Coors Field", "city": "Denver", "state": "Colorado", "abbreviation": "COL", "team_id": "colorado-rockies", "full_name": "Colorado Rockies", "active": true}, "away_pitchers": [{"last_name": "Flande", "win": false, "runs_allowed": 3, "hit_by_pitch": 0, "walks": 1, "intentional_walks": 0, "whip": 1.31, "first_name": "Yohan", "errors": 0, "display_name": "Yohan Flande", "pitches_strikes": 54, "innings_pitched": 5.1, "save": false, "era": 5.06, "wild_pitches": 0, "home_runs_allowed": 0, "pitch_order": 1, "hits_allowed": 6, "hold": false, "loss": true, "earned_runs": 3, "team_abbreviation": "COL", "pitch_count": 87, "strike_outs": 3}, {"last_name": "Scahill", "win": false, "runs_allowed": 4, "hit_by_pitch": 1, "walks": 2, "intentional_walks": 1, "whip": 3.0, "first_name": "Robert", "errors": 0, "display_name": "Rob Scahill", "pitches_strikes": 22, "innings_pitched": 1.2, "save": false, "era": 21.6, "wild_pitches": 0, "home_runs_allowed": 1, "pitch_order": 2, "hits_allowed": 3, "hold": false, "loss": false, "earned_runs": 4, "team_abbreviation": "COL", "pitch_count": 38, "strike_outs": 1}, {"last_name": "Masset", "win": false, "runs_allowed": 0, "hit_by_pitch": 0, "walks": 0, "intentional_walks": 0, "whip": 0.0, "first_name": "Nicholas", "errors": 0, "display_name": "Nick Masset", "pitches_strikes": 9, "innings_pitched": 1.0, "save": false, "era": 0.0, "wild_pitches": 0, "home_runs_allowed": 0, "pitch_order": 3, "hits_allowed": 0, "hold": false, "loss": false, "earned_runs": 0, "team_abbreviation": "COL", "pitch_count": 11, "strike_outs": 1}], "away_batter_totals": {"sac_hits": 1, "slg_string": ".344", "rbi_with_two_outs": 0, "batting_highlights": "9-32, 3 R, 2 RBI, 2 2B", "sac_flies": 1, "total_bases": 11, "caught_stealing": 1, "hit_by_pitch": 0, "home_runs": 0, "avg_string": ".281", "avg": 0.281, "extra_base_hits": 2, "at_bats": 32, "ops": 0.65, "plate_appearances_per_home_run": 0.0, "walks": 2, "ops_string": ".650", "stolen_base_average": 0.0, "triples": 0, "left_on_base": 15, "singles": 7, "stolen_bases": 0, "hits": 9, "plate_appearances_per_rbi": 18.0, "doubles": 2, "plate_appearances": 36, "at_bats_per_home_run": 0.0, "obp_string": ".306", "runs": 3, "at_bats_per_rbi": 16.0, "strikeout_rate": 0.188, "sacrifices": 2, "walk_rate": 0.056, "rbi": 2, "strike_outs": 6, "slg": 0.344, "obp": 0.306}, "home_period_scores": [0, 0, 0, 1, 0, 5, 1, 0, -1], "away_batters": [{"sac_hits": 0, "slg_string": ".250", "last_name": "Blackmon", "rbi_with_two_outs": 0, "batting_highlights": "1-4", "sub_bat_order": 0, "sac_flies": 0, "total_bases": 1, "caught_stealing": 0, "team_abbreviation": "COL", "hit_by_pitch": 0, "home_runs": 0, "avg_string": ".250", "avg": 0.25, "extra_base_hits": 0, "first_name": "Charlie", "display_name": "Charlie Blackmon", "at_bats": 4, "ops": 0.5, "plate_appearances_per_home_run": 0.0, "walks": 0, "ops_string": ".500", "stolen_base_average": 0.0, "bat_order": 1, "triples": 0, "left_on_base": 3, "singles": 1, "stolen_bases": 0, "hits": 1, "plate_appearances_per_rbi": 0.0, "position": "LF-RF", "plate_appearances": 4, "at_bats_per_home_run": 0.0, "obp_string": ".250", "runs": 0, "at_bats_per_rbi": 0.0, "strike_outs": 0, "strikeout_rate": 0.0, "sacrifices": 0, "walk_rate": 0.0, "rbi": 0, "doubles": 0, "slg": 0.25, "obp": 0.25}, {"sac_hits": 0, "slg_string": ".500", "last_name": "Stubbs", "rbi_with_two_outs": 0, "batting_highlights": "1-4, R, 2B", "sub_bat_order": 0, "sac_flies": 0, "total_bases": 2, "caught_stealing": 0, "team_abbreviation": "COL", "hit_by_pitch": 0, "home_runs": 0, "avg_string": ".250", "avg": 0.25, "extra_base_hits": 1, "first_name": "Robert", "display_name": "Drew Stubbs", "at_bats": 4, "ops": 0.75, "plate_appearances_per_home_run": 0.0, "walks": 0, "ops_string": ".750", "stolen_base_average": 0.0, "bat_order": 2, "triples": 0, "left_on_base": 2, "singles": 0, "stolen_bases": 0, "hits": 1, "plate_appearances_per_rbi": 0.0, "position": "CF", "plate_appearances": 4, "at_bats_per_home_run": 0.0, "obp_string": ".250", "runs": 1, "at_bats_per_rbi": 0.0, "strike_outs": 1, "strikeout_rate": 0.25, "sacrifices": 0, "walk_rate": 0.0, "rbi": 0, "doubles": 1, "slg": 0.5, "obp": 0.25}, {"sac_hits": 0, "slg_string": ".667", "last_name": "Tulowitzki", "rbi_with_two_outs": 0, "batting_highlights": "1-3, 2 R, RBI, 2B", "sub_bat_order": 0, "sac_flies": 0, "total_bases": 2, "caught_stealing": 0, "team_abbreviation": "COL", "hit_by_pitch": 0, "home_runs": 0, "avg_string": ".333", "avg": 0.333, "extra_base_hits": 1, "first_name": "Troy", "display_name": "Troy Tulowitzki", "at_bats": 3, "ops": 1.167, "plate_appearances_per_home_run": 0.0, "walks": 1, "ops_string": "1.167", "stolen_base_average": 0.0, "bat_order": 3, "triples": 0, "left_on_base": 2, "singles": 0, "stolen_bases": 0, "hits": 1, "plate_appearances_per_rbi": 4.0, "position": "SS", "plate_appearances": 4, "at_bats_per_home_run": 0.0, "obp_string": ".500", "runs": 2, "at_bats_per_rbi": 3.0, "strike_outs": 1, "strikeout_rate": 0.333, "sacrifices": 0, "walk_rate": 0.25, "rbi": 1, "doubles": 1, "slg": 0.667, "obp": 0.5}, {"sac_hits": 0, "slg_string": ".750", "last_name": "Morneau", "rbi_with_two_outs": 0, "batting_highlights": "3-4", "sub_bat_order": 0, "sac_flies": 0, "total_bases": 3, "caught_stealing": 0, "team_abbreviation": "COL", "hit_by_pitch": 0, "home_runs": 0, "avg_string": ".750", "avg": 0.75, "extra_base_hits": 0, "first_name": "Justin", "display_name": "Justin Morneau", "at_bats": 4, "ops": 1.5, "plate_appearances_per_home_run": 0.0, "walks": 0, "ops_string": "1.500", "stolen_base_average": 0.0, "bat_order": 4, "triples": 0, "left_on_base": 0, "singles": 3, "stolen_bases": 0, "hits": 3, "plate_appearances_per_rbi": 0.0, "position": "1B", "plate_appearances": 4, "at_bats_per_home_run": 0.0, "obp_string": ".750", "runs": 0, "at_bats_per_rbi": 0.0, "strike_outs": 0, "strikeout_rate": 0.0, "sacrifices": 0, "walk_rate": 0.0, "rbi": 0, "doubles": 0, "slg": 0.75, "obp": 0.75}, {"sac_hits": 0, "slg_string": ".000", "last_name": "Rosario", "rbi_with_two_outs": 0, "batting_highlights": "0-4", "sub_bat_order": 0, "sac_flies": 0, "total_bases": 0, "caught_stealing": 0, "team_abbreviation": "COL", "hit_by_pitch": 0, "home_runs": 0, "avg_string": ".000", "avg": 0.0, "extra_base_hits": 0, "first_name": "Wilin", "display_name": "Wilin Rosario", "at_bats": 4, "ops": 0.0, "plate_appearances_per_home_run": 0.0, "walks": 0, "ops_string": ".000", "stolen_base_average": 0.0, "bat_order": 5, "triples": 0, "left_on_base": 6, "singles": 0, "stolen_bases": 0, "hits": 0, "plate_appearances_per_rbi": 0.0, "position": "C", "plate_appearances": 4, "at_bats_per_home_run": 0.0, "obp_string": ".000", "runs": 0, "at_bats_per_rbi": 0.0, "strike_outs": 1, "strikeout_rate": 0.25, "sacrifices": 0, "walk_rate": 0.0, "rbi": 0, "doubles": 0, "slg": 0.0, "obp": 0.0}, {"sac_hits": 0, "slg_string": ".000", "last_name": "Wheeler", "rbi_with_two_outs": 0, "batting_highlights": "0-3, RBI", "sub_bat_order": 0, "sac_flies": 1, "total_bases": 0, "caught_stealing": 0, "team_abbreviation": "COL", "hit_by_pitch": 0, "home_runs": 0, "avg_string": ".000", "avg": 0.0, "extra_base_hits": 0, "first_name": "Ryan", "display_name": "Ryan Wheeler", "at_bats": 3, "ops": 0.0, "plate_appearances_per_home_run": 0.0, "walks": 0, "ops_string": ".000", "stolen_base_average": 0.0, "bat_order": 6, "triples": 0, "left_on_base": 1, "singles": 0, "stolen_bases": 0, "hits": 0, "plate_appearances_per_rbi": 4.0, "position": "3B", "plate_appearances": 4, "at_bats_per_home_run": 0.0, "obp_string": ".000", "runs": 0, "at_bats_per_rbi": 3.0, "strike_outs": 1, "strikeout_rate": 0.333, "sacrifices": 1, "walk_rate": 0.0, "rbi": 1, "doubles": 0, "slg": 0.0, "obp": 0.0}, {"sac_hits": 0, "slg_string": ".333", "last_name": "Barnes", "rbi_with_two_outs": 0, "batting_highlights": "1-3", "sub_bat_order": 0, "sac_flies": 0, "total_bases": 1, "caught_stealing": 1, "team_abbreviation": "COL", "hit_by_pitch": 0, "home_runs": 0, "avg_string": ".333", "avg": 0.333, "extra_base_hits": 0, "first_name": "Brandon", "display_name": "Brandon Barnes", "at_bats": 3, "ops": 0.666, "plate_appearances_per_home_run": 0.0, "walks": 0, "ops_string": ".666", "stolen_base_average": 0.0, "bat_order": 7, "triples": 0, "left_on_base": 1, "singles": 1, "stolen_bases": 0, "hits": 1, "plate_appearances_per_rbi": 0.0, "position": "RF", "plate_appearances": 3, "at_bats_per_home_run": 0.0, "obp_string": ".333", "runs": 0, "at_bats_per_rbi": 0.0, "strike_outs": 1, "strikeout_rate": 0.333, "sacrifices": 0, "walk_rate": 0.0, "rbi": 0, "doubles": 0, "slg": 0.333, "obp": 0.333}, {"sac_hits": 0, "slg_string": ".000", "last_name": "Scahill", "rbi_with_two_outs": 0, "batting_highlights": "0-0", "sub_bat_order": 1, "sac_flies": 0, "total_bases": 0, "caught_stealing": 0, "team_abbreviation": "COL", "hit_by_pitch": 0, "home_runs": 0, "avg_string": ".000", "avg": 0.0, "extra_base_hits": 0, "first_name": "Robert", "display_name": "Rob Scahill", "at_bats": 0, "ops": 0.0, "plate_appearances_per_home_run": 0.0, "walks": 0, "ops_string": ".000", "stolen_base_average": 0.0, "bat_order": 7, "triples": 0, "left_on_base": 0, "singles": 0, "stolen_bases": 0, "hits": 0, "plate_appearances_per_rbi": 0.0, "position": "P", "plate_appearances": 0, "at_bats_per_home_run": 0.0, "obp_string": ".000", "runs": 0, "at_bats_per_rbi": 0.0, "strike_outs": 0, "strikeout_rate": 0.0, "sacrifices": 0, "walk_rate": 0.0, "rbi": 0, "doubles": 0, "slg": 0.0, "obp": 0.0}, {"sac_hits": 0, "slg_string": ".000", "last_name": "Masset", "rbi_with_two_outs": 0, "batting_highlights": "0-0", "sub_bat_order": 2, "sac_flies": 0, "total_bases": 0, "caught_stealing": 0, "team_abbreviation": "COL", "hit_by_pitch": 0, "home_runs": 0, "avg_string": ".000", "avg": 0.0, "extra_base_hits": 0, "first_name": "Nicholas", "display_name": "Nick Masset", "at_bats": 0, "ops": 0.0, "plate_appearances_per_home_run": 0.0, "walks": 0, "ops_string": ".000", "stolen_base_average": 0.0, "bat_order": 7, "triples": 0, "left_on_base": 0, "singles": 0, "stolen_bases": 0, "hits": 0, "plate_appearances_per_rbi": 0.0, "position": "P", "plate_appearances": 0, "at_bats_per_home_run": 0.0, "obp_string": ".000", "runs": 0, "at_bats_per_rbi": 0.0, "strike_outs": 0, "strikeout_rate": 0.0, "sacrifices": 0, "walk_rate": 0.0, "rbi": 0, "doubles": 0, "slg": 0.0, "obp": 0.0}, {"sac_hits": 0, "slg_string": ".000", "last_name": "Rutledge", "rbi_with_two_outs": 0, "batting_highlights": "0-1", "sub_bat_order": 3, "sac_flies": 0, "total_bases": 0, "caught_stealing": 0, "team_abbreviation": "COL", "hit_by_pitch": 0, "home_runs": 0, "avg_string": ".000", "avg": 0.0, "extra_base_hits": 0, "first_name": "Joshua", "display_name": "Josh Rutledge", "at_bats": 1, "ops": 0.0, "plate_appearances_per_home_run": 0.0, "walks": 0, "ops_string": ".000", "stolen_base_average": 0.0, "bat_order": 7, "triples": 0, "left_on_base": 0, "singles": 0, "stolen_bases": 0, "hits": 0, "plate_appearances_per_rbi": 0.0, "position": "PH", "plate_appearances": 1, "at_bats_per_home_run": 0.0, "obp_string": ".000", "runs": 0, "at_bats_per_rbi": 0.0, "strike_outs": 0, "strikeout_rate": 0.0, "sacrifices": 0, "walk_rate": 0.0, "rbi": 0, "doubles": 0, "slg": 0.0, "obp": 0.0}, {"sac_hits": 0, "slg_string": ".250", "last_name": "LeMahieu", "rbi_with_two_outs": 0, "batting_highlights": "1-4", "sub_bat_order": 0, "sac_flies": 0, "total_bases": 1, "caught_stealing": 0, "team_abbreviation": "COL", "hit_by_pitch": 0, "home_runs": 0, "avg_string": ".250", "avg": 0.25, "extra_base_hits": 0, "first_name": "David", "display_name": "D.J. LeMahieu", "at_bats": 4, "ops": 0.5, "plate_appearances_per_home_run": 0.0, "walks": 0, "ops_string": ".500", "stolen_base_average": 0.0, "bat_order": 8, "triples": 0, "left_on_base": 0, "singles": 1, "stolen_bases": 0, "hits": 1, "plate_appearances_per_rbi": 0.0, "position": "2B", "plate_appearances": 4, "at_bats_per_home_run": 0.0, "obp_string": ".250", "runs": 0, "at_bats_per_rbi": 0.0, "strike_outs": 1, "strikeout_rate": 0.25, "sacrifices": 0, "walk_rate": 0.0, "rbi": 0, "doubles": 0, "slg": 0.25, "obp": 0.25}, {"sac_hits": 1, "slg_string": ".000", "last_name": "Flande", "rbi_with_two_outs": 0, "batting_highlights": "0-0", "sub_bat_order": 0, "sac_flies": 0, "total_bases": 0, "caught_stealing": 0, "team_abbreviation": "COL", "hit_by_pitch": 0, "home_runs": 0, "avg_string": ".000", "avg": 0.0, "extra_base_hits": 0, "first_name": "Yohan", "display_name": "Yohan Flande", "at_bats": 0, "ops": 0.5, "plate_appearances_per_home_run": 0.0, "walks": 1, "ops_string": ".500", "stolen_base_average": 0.0, "bat_order": 9, "triples": 0, "left_on_base": 0, "singles": 0, "stolen_bases": 0, "hits": 0, "plate_appearances_per_rbi": 0.0, "position": "P", "plate_appearances": 2, "at_bats_per_home_run": 0.0, "obp_string": ".500", "runs": 0, "at_bats_per_rbi": 0.0, "strike_outs": 0, "strikeout_rate": 0.0, "sacrifices": 1, "walk_rate": 0.5, "rbi": 0, "doubles": 0, "slg": 0.0, "obp": 0.5}, {"sac_hits": 0, "slg_string": ".500", "last_name": "Dickerson", "rbi_with_two_outs": 0, "batting_highlights": "1-2", "sub_bat_order": 1, "sac_flies": 0, "total_bases": 1, "caught_stealing": 0, "team_abbreviation": "COL", "hit_by_pitch": 0, "home_runs": 0, "avg_string": ".500", "avg": 0.5, "extra_base_hits": 0, "first_name": "McKenzie", "display_name": "Corey Dickerson", "at_bats": 2, "ops": 1.0, "plate_appearances_per_home_run": 0.0, "walks": 0, "ops_string": "1.000", "stolen_base_average": 0.0, "bat_order": 9, "triples": 0, "left_on_base": 0, "singles": 1, "stolen_bases": 0, "hits": 1, "plate_appearances_per_rbi": 0.0, "position": "LF", "plate_appearances": 2, "at_bats_per_home_run": 0.0, "obp_string": ".500", "runs": 0, "at_bats_per_rbi": 0.0, "strike_outs": 0, "strikeout_rate": 0.0, "sacrifices": 0, "walk_rate": 0.0, "rbi": 0, "doubles": 0, "slg": 0.5, "obp": 0.5}], "home_batter_totals": {"sac_hits": 1, "slg_string": ".516", "rbi_with_two_outs": 1, "batting_highlights": "9-31, HR, 7 R, 7 RBI, 4 2B, SB", "sac_flies": 0, "total_bases": 16, "caught_stealing": 0, "hit_by_pitch": 1, "home_runs": 1, "avg_string": ".290", "avg": 0.29, "extra_base_hits": 5, "at_bats": 31, "ops": 0.877, "plate_appearances_per_home_run": 36.0, "walks": 3, "ops_string": ".877", "stolen_base_average": 1.0, "triples": 0, "left_on_base": 10, "singles": 4, "stolen_bases": 1, "hits": 9, "plate_appearances_per_rbi": 5.143, "doubles": 4, "plate_appearances": 36, "at_bats_per_home_run": 31.0, "obp_string": ".361", "runs": 7, "at_bats_per_rbi": 4.429, "strikeout_rate": 0.161, "sacrifices": 1, "walk_rate": 0.083, "rbi": 7, "strike_outs": 5, "slg": 0.516, "obp": 0.361}, "away_period_scores": [0, 0, 0, 0, 0, 2, 0, 1, 0], "home_batters": [{"sac_hits": 0, "slg_string": ".000", "last_name": "Span", "rbi_with_two_outs": 0, "batting_highlights": "0-3", "sub_bat_order": 0, "sac_flies": 0, "total_bases": 0, "caught_stealing": 0, "team_abbreviation": "WAS", "hit_by_pitch": 0, "home_runs": 0, "avg_string": ".000", "avg": 0.0, "extra_base_hits": 0, "first_name": "Denard", "display_name": "Denard Span", "at_bats": 3, "ops": 0.25, "plate_appearances_per_home_run": 0.0, "walks": 1, "ops_string": ".250", "stolen_base_average": 0.0, "bat_order": 1, "triples": 0, "left_on_base": 2, "singles": 0, "stolen_bases": 0, "hits": 0, "plate_appearances_per_rbi": 0.0, "position": "CF", "plate_appearances": 4, "at_bats_per_home_run": 0.0, "obp_string": ".250", "runs": 0, "at_bats_per_rbi": 0.0, "strike_outs": 1, "strikeout_rate": 0.333, "sacrifices": 0, "walk_rate": 0.25, "rbi": 0, "doubles": 0, "slg": 0.0, "obp": 0.25}, {"sac_hits": 0, "slg_string": ".250", "last_name": "Rendon", "rbi_with_two_outs": 0, "batting_highlights": "1-4, R", "sub_bat_order": 0, "sac_flies": 0, "total_bases": 1, "caught_stealing": 0, "team_abbreviation": "WAS", "hit_by_pitch": 0, "home_runs": 0, "avg_string": ".250", "avg": 0.25, "extra_base_hits": 0, "first_name": "Anthony", "display_name": "Anthony Rendon", "at_bats": 4, "ops": 0.5, "plate_appearances_per_home_run": 0.0, "walks": 0, "ops_string": ".500", "stolen_base_average": 0.0, "bat_order": 2, "triples": 0, "left_on_base": 4, "singles": 1, "stolen_bases": 0, "hits": 1, "plate_appearances_per_rbi": 0.0, "position": "2B", "plate_appearances": 4, "at_bats_per_home_run": 0.0, "obp_string": ".250", "runs": 1, "at_bats_per_rbi": 0.0, "strike_outs": 1, "strikeout_rate": 0.25, "sacrifices": 0, "walk_rate": 0.0, "rbi": 0, "doubles": 0, "slg": 0.25, "obp": 0.25}, {"sac_hits": 0, "slg_string": ".000", "last_name": "Werth", "rbi_with_two_outs": 0, "batting_highlights": "0-3, R", "sub_bat_order": 0, "sac_flies": 0, "total_bases": 0, "caught_stealing": 0, "team_abbreviation": "WAS", "hit_by_pitch": 0, "home_runs": 0, "avg_string": ".000", "avg": 0.0, "extra_base_hits": 0, "first_name": "Jayson", "display_name": "Jayson Werth", "at_bats": 3, "ops": 0.25, "plate_appearances_per_home_run": 0.0, "walks": 1, "ops_string": ".250", "stolen_base_average": 0.0, "bat_order": 3, "triples": 0, "left_on_base": 0, "singles": 0, "stolen_bases": 0, "hits": 0, "plate_appearances_per_rbi": 0.0, "position": "RF", "plate_appearances": 4, "at_bats_per_home_run": 0.0, "obp_string": ".250", "runs": 1, "at_bats_per_rbi": 0.0, "strike_outs": 0, "strikeout_rate": 0.0, "sacrifices": 0, "walk_rate": 0.25, "rbi": 0, "doubles": 0, "slg": 0.0, "obp": 0.25}, {"sac_hits": 0, "slg_string": "1.000", "last_name": "LaRoche", "rbi_with_two_outs": 0, "batting_highlights": "1-4, HR, R, RBI", "sub_bat_order": 0, "sac_flies": 0, "total_bases": 4, "caught_stealing": 0, "team_abbreviation": "WAS", "hit_by_pitch": 0, "home_runs": 1, "avg_string": ".250", "avg": 0.25, "extra_base_hits": 1, "first_name": "David", "display_name": "Adam LaRoche", "at_bats": 4, "ops": 1.25, "plate_appearances_per_home_run": 4.0, "walks": 0, "ops_string": "1.250", "stolen_base_average": 0.0, "bat_order": 4, "triples": 0, "left_on_base": 2, "singles": 0, "stolen_bases": 0, "hits": 1, "plate_appearances_per_rbi": 4.0, "position": "1B", "plate_appearances": 4, "at_bats_per_home_run": 4.0, "obp_string": ".250", "runs": 1, "at_bats_per_rbi": 4.0, "strike_outs": 1, "strikeout_rate": 0.25, "sacrifices": 0, "walk_rate": 0.0, "rbi": 1, "doubles": 0, "slg": 1.0, "obp": 0.25}, {"sac_hits": 0, "slg_string": "1.250", "last_name": "Zimmerman", "rbi_with_two_outs": 0, "batting_highlights": "3-4, 2 R, RBI, 2 2B", "sub_bat_order": 0, "sac_flies": 0, "total_bases": 5, "caught_stealing": 0, "team_abbreviation": "WAS", "hit_by_pitch": 0, "home_runs": 0, "avg_string": ".750", "avg": 0.75, "extra_base_hits": 2, "first_name": "Ryan", "display_name": "Ryan Zimmerman", "at_bats": 4, "ops": 2.0, "plate_appearances_per_home_run": 0.0, "walks": 0, "ops_string": "2.000", "stolen_base_average": 0.0, "bat_order": 5, "triples": 0, "left_on_base": 0, "singles": 1, "stolen_bases": 0, "hits": 3, "plate_appearances_per_rbi": 4.0, "position": "3B", "plate_appearances": 4, "at_bats_per_home_run": 0.0, "obp_string": ".750", "runs": 2, "at_bats_per_rbi": 4.0, "strike_outs": 0, "strikeout_rate": 0.0, "sacrifices": 0, "walk_rate": 0.0, "rbi": 1, "doubles": 2, "slg": 1.25, "obp": 0.75}, {"sac_hits": 0, "slg_string": ".333", "last_name": "Harper", "rbi_with_two_outs": 1, "batting_highlights": "1-3, R, RBI", "sub_bat_order": 0, "sac_flies": 0, "total_bases": 1, "caught_stealing": 0, "team_abbreviation": "WAS", "hit_by_pitch": 0, "home_runs": 0, "avg_string": ".333", "avg": 0.333, "extra_base_hits": 0, "first_name": "Bryce", "display_name": "Bryce Harper", "at_bats": 3, "ops": 0.833, "plate_appearances_per_home_run": 0.0, "walks": 1, "ops_string": ".833", "stolen_base_average": 0.0, "bat_order": 6, "triples": 0, "left_on_base": 1, "singles": 1, "stolen_bases": 0, "hits": 1, "plate_appearances_per_rbi": 4.0, "position": "LF", "plate_appearances": 4, "at_bats_per_home_run": 0.0, "obp_string": ".500", "runs": 1, "at_bats_per_rbi": 3.0, "strike_outs": 0, "strikeout_rate": 0.0, "sacrifices": 0, "walk_rate": 0.25, "rbi": 1, "doubles": 0, "slg": 0.333, "obp": 0.5}, {"sac_hits": 0, "slg_string": "1.000", "last_name": "Desmond", "rbi_with_two_outs": 0, "batting_highlights": "2-4, R, 3 RBI, 2 2B, SB", "sub_bat_order": 0, "sac_flies": 0, "total_bases": 4, "caught_stealing": 0, "team_abbreviation": "WAS", "hit_by_pitch": 0, "home_runs": 0, "avg_string": ".500", "avg": 0.5, "extra_base_hits": 2, "first_name": "Ian", "display_name": "Ian Desmond", "at_bats": 4, "ops": 1.5, "plate_appearances_per_home_run": 0.0, "walks": 0, "ops_string": "1.500", "stolen_base_average": 1.0, "bat_order": 7, "triples": 0, "left_on_base": 1, "singles": 0, "stolen_bases": 1, "hits": 2, "plate_appearances_per_rbi": 1.333, "position": "SS", "plate_appearances": 4, "at_bats_per_home_run": 0.0, "obp_string": ".500", "runs": 1, "at_bats_per_rbi": 1.333, "strike_outs": 1, "strikeout_rate": 0.25, "sacrifices": 0, "walk_rate": 0.0, "rbi": 3, "doubles": 2, "slg": 1.0, "obp": 0.5}, {"sac_hits": 0, "slg_string": ".250", "last_name": "Ramos", "rbi_with_two_outs": 0, "batting_highlights": "1-4, RBI", "sub_bat_order": 0, "sac_flies": 0, "total_bases": 1, "caught_stealing": 0, "team_abbreviation": "WAS", "hit_by_pitch": 0, "home_runs": 0, "avg_string": ".250", "avg": 0.25, "extra_base_hits": 0, "first_name": "Wilson", "display_name": "Wilson Ramos", "at_bats": 4, "ops": 0.5, "plate_appearances_per_home_run": 0.0, "walks": 0, "ops_string": ".500", "stolen_base_average": 0.0, "bat_order": 8, "triples": 0, "left_on_base": 0, "singles": 1, "stolen_bases": 0, "hits": 1, "plate_appearances_per_rbi": 4.0, "position": "C", "plate_appearances": 4, "at_bats_per_home_run": 0.0, "obp_string": ".250", "runs": 0, "at_bats_per_rbi": 4.0, "strike_outs": 0, "strikeout_rate": 0.0, "sacrifices": 0, "walk_rate": 0.0, "rbi": 1, "doubles": 0, "slg": 0.25, "obp": 0.25}, {"sac_hits": 1, "slg_string": ".000", "last_name": "Zimmermann", "rbi_with_two_outs": 0, "batting_highlights": "0-1", "sub_bat_order": 0, "sac_flies": 0, "total_bases": 0, "caught_stealing": 0, "team_abbreviation": "WAS", "hit_by_pitch": 0, "home_runs": 0, "avg_string": ".000", "avg": 0.0, "extra_base_hits": 0, "first_name": "Jordan", "display_name": "Jordan Zimmermann", "at_bats": 1, "ops": 0.0, "plate_appearances_per_home_run": 0.0, "walks": 0, "ops_string": ".000", "stolen_base_average": 0.0, "bat_order": 9, "triples": 0, "left_on_base": 0, "singles": 0, "stolen_bases": 0, "hits": 0, "plate_appearances_per_rbi": 0.0, "position": "P", "plate_appearances": 2, "at_bats_per_home_run": 0.0, "obp_string": ".000", "runs": 0, "at_bats_per_rbi": 0.0, "strike_outs": 0, "strikeout_rate": 0.0, "sacrifices": 1, "walk_rate": 0.0, "rbi": 0, "doubles": 0, "slg": 0.0, "obp": 0.0}, {"sac_hits": 0, "slg_string": ".000", "last_name": "Frandsen", "rbi_with_two_outs": 0, "batting_highlights": "0-0", "sub_bat_order": 1, "sac_flies": 0, "total_bases": 0, "caught_stealing": 0, "team_abbreviation": "WAS", "hit_by_pitch": 1, "home_runs": 0, "avg_string": ".000", "avg": 0.0, "extra_base_hits": 0, "first_name": "Kevin", "display_name": "Kevin Frandsen", "at_bats": 0, "ops": 1.0, "plate_appearances_per_home_run": 0.0, "walks": 0, "ops_string": "1.000", "stolen_base_average": 0.0, "bat_order": 9, "triples": 0, "left_on_base": 0, "singles": 0, "stolen_bases": 0, "hits": 0, "plate_appearances_per_rbi": 0.0, "position": "PH", "plate_appearances": 1, "at_bats_per_home_run": 0.0, "obp_string": "1.000", "runs": 0, "at_bats_per_rbi": 0.0, "strike_outs": 0, "strikeout_rate": 0.0, "sacrifices": 0, "walk_rate": 0.0, "rbi": 0, "doubles": 0, "slg": 0.0, "obp": 1.0}, {"sac_hits": 0, "slg_string": ".000", "last_name": "Storen", "rbi_with_two_outs": 0, "batting_highlights": "0-0", "sub_bat_order": 2, "sac_flies": 0, "total_bases": 0, "caught_stealing": 0, "team_abbreviation": "WAS", "hit_by_pitch": 0, "home_runs": 0, "avg_string": ".000", "avg": 0.0, "extra_base_hits": 0, "first_name": "Drew", "display_name": "Drew Storen", "at_bats": 0, "ops": 0.0, "plate_appearances_per_home_run": 0.0, "walks": 0, "ops_string": ".000", "stolen_base_average": 0.0, "bat_order": 9, "triples": 0, "left_on_base": 0, "singles": 0, "stolen_bases": 0, "hits": 0, "plate_appearances_per_rbi": 0.0, "position": "P", "plate_appearances": 0, "at_bats_per_home_run": 0.0, "obp_string": ".000", "runs": 0, "at_bats_per_rbi": 0.0, "strike_outs": 0, "strikeout_rate": 0.0, "sacrifices": 0, "walk_rate": 0.0, "rbi": 0, "doubles": 0, "slg": 0.0, "obp": 0.0}, {"sac_hits": 0, "slg_string": ".000", "last_name": "Barrett", "rbi_with_two_outs": 0, "batting_highlights": "0-0", "sub_bat_order": 3, "sac_flies": 0, "total_bases": 0, "caught_stealing": 0, "team_abbreviation": "WAS", "hit_by_pitch": 0, "home_runs": 0, "avg_string": ".000", "avg": 0.0, "extra_base_hits": 0, "first_name": "Aaron", "display_name": "Aaron Barrett", "at_bats": 0, "ops": 0.0, "plate_appearances_per_home_run": 0.0, "walks": 0, "ops_string": ".000", "stolen_base_average": 0.0, "bat_order": 9, "triples": 0, "left_on_base": 0, "singles": 0, "stolen_bases": 0, "hits": 0, "plate_appearances_per_rbi": 0.0, "position": "P", "plate_appearances": 0, "at_bats_per_home_run": 0.0, "obp_string": ".000", "runs": 0, "at_bats_per_rbi": 0.0, "strike_outs": 0, "strikeout_rate": 0.0, "sacrifices": 0, "walk_rate": 0.0, "rbi": 0, "doubles": 0, "slg": 0.0, "obp": 0.0}, {"sac_hits": 0, "slg_string": ".000", "last_name": "Hairston", "rbi_with_two_outs": 0, "batting_highlights": "0-1", "sub_bat_order": 4, "sac_flies": 0, "total_bases": 0, "caught_stealing": 0, "team_abbreviation": "WAS", "hit_by_pitch": 0, "home_runs": 0, "avg_string": ".000", "avg": 0.0, "extra_base_hits": 0, "first_name": "Scott", "display_name": "Scott Hairston", "at_bats": 1, "ops": 0.0, "plate_appearances_per_home_run": 0.0, "walks": 0, "ops_string": ".000", "stolen_base_average": 0.0, "bat_order": 9, "triples": 0, "left_on_base": 0, "singles": 0, "stolen_bases": 0, "hits": 0, "plate_appearances_per_rbi": 0.0, "position": "PH", "plate_appearances": 1, "at_bats_per_home_run": 0.0, "obp_string": ".000", "runs": 0, "at_bats_per_rbi": 0.0, "strike_outs": 1, "strikeout_rate": 1.0, "sacrifices": 0, "walk_rate": 0.0, "rbi": 0, "doubles": 0, "slg": 0.0, "obp": 0.0}, {"sac_hits": 0, "slg_string": ".000", "last_name": "Blevins", "rbi_with_two_outs": 0, "batting_highlights": "0-0", "sub_bat_order": 5, "sac_flies": 0, "total_bases": 0, "caught_stealing": 0, "team_abbreviation": "WAS", "hit_by_pitch": 0, "home_runs": 0, "avg_string": ".000", "avg": 0.0, "extra_base_hits": 0, "first_name": "Jerry", "display_name": "Jerry Blevins", "at_bats": 0, "ops": 0.0, "plate_appearances_per_home_run": 0.0, "walks": 0, "ops_string": ".000", "stolen_base_average": 0.0, "bat_order": 9, "triples": 0, "left_on_base": 0, "singles": 0, "stolen_bases": 0, "hits": 0, "plate_appearances_per_rbi": 0.0, "position": "P", "plate_appearances": 0, "at_bats_per_home_run": 0.0, "obp_string": ".000", "runs": 0, "at_bats_per_rbi": 0.0, "strike_outs": 0, "strikeout_rate": 0.0, "sacrifices": 0, "walk_rate": 0.0, "rbi": 0, "doubles": 0, "slg": 0.0, "obp": 0.0}], "officials": [{"position": "Home Plate", "first_name": "Joe", "last_name": "West"}, {"position": "First Base", "first_name": "Marty", "last_name": "Foster"}, {"position": "Second Base", "first_name": "Rob", "last_name": "Drake"}, {"position": "Third Base", "first_name": "Alan", "last_name": "Porter"}], "event_information": {"start_date_time": "2014-06-30T19:05:00-04:00", "attendance": 33660, "temperature": 86, "season_type": "regular", "site": {"city": "Washington", "state": "District of Columbia", "capacity": 41487, "name": "Nationals Park", "surface": "Grass"}, "duration": "2:58"}, "home_pitchers": [{"last_name": "Zimmermann", "win": true, "runs_allowed": 2, "hit_by_pitch": 0, "walks": 1, "intentional_walks": 0, "whip": 1.33, "first_name": "Jordan", "errors": 0, "display_name": "Jordan Zimmermann", "pitches_strikes": 60, "innings_pitched": 6.0, "save": false, "era": 3.0, "wild_pitches": 0, "home_runs_allowed": 0, "pitch_order": 1, "hits_allowed": 7, "hold": false, "loss": false, "earned_runs": 2, "team_abbreviation": "WAS", "pitch_count": 87, "strike_outs": 5}, {"last_name": "Storen", "win": false, "runs_allowed": 0, "hit_by_pitch": 0, "walks": 0, "intentional_walks": 0, "whip": 1.0, "first_name": "Drew", "errors": 0, "display_name": "Drew Storen", "pitches_strikes": 7, "innings_pitched": 1.0, "save": false, "era": 0.0, "wild_pitches": 0, "home_runs_allowed": 0, "pitch_order": 2, "hits_allowed": 1, "hold": false, "loss": false, "earned_runs": 0, "team_abbreviation": "WAS", "pitch_count": 9, "strike_outs": 0}, {"last_name": "Barrett", "win": false, "runs_allowed": 1, "hit_by_pitch": 0, "walks": 1, "intentional_walks": 0, "whip": 2.0, "first_name": "Aaron", "errors": 0, "display_name": "Aaron Barrett", "pitches_strikes": 5, "innings_pitched": 1.0, "save": false, "era": 9.0, "wild_pitches": 1, "home_runs_allowed": 0, "pitch_order": 3, "hits_allowed": 1, "hold": false, "loss": false, "earned_runs": 1, "team_abbreviation": "WAS", "pitch_count": 14, "strike_outs": 0}, {"last_name": "Blevins", "win": false, "runs_allowed": 0, "hit_by_pitch": 0, "walks": 0, "intentional_walks": 0, "whip": 0.0, "first_name": "Jerry", "errors": 0, "display_name": "Jerry Blevins", "pitches_strikes": 10, "innings_pitched": 1.0, "save": false, "era": 0.0, "wild_pitches": 0, "home_runs_allowed": 0, "pitch_order": 4, "hits_allowed": 0, "hold": false, "loss": false, "earned_runs": 0, "team_abbreviation": "WAS", "pitch_count": 11, "strike_outs": 1}]}